hydra_trainer/__init__.py
hydra_trainer/base.yaml
hydra_trainer-0.1.2.dist-info/METADATA
hydra_trainer-0.1.2.dist-info/WHEEL
hydra_trainer-0.1.2.dist-info/top_level.txt
hydra_trainer-0.1.2.dist-info/RECORD
