Metadata-Version: 2.2
Name: hydra_trainer
Version: 0.1.2
Summary: Hugging Face transformers with Hydra integration
Author-email: Emmanuel Cortes <manny@derifyai.com>
Maintainer-email: Emmanuel Cortes <manny@derifyai.com>
License: Apache 2.0
Project-URL: Repository, https://github.com/emapco/HydraTrainer
Requires-Python: >=3.11
Requires-Dist: transformers>=4.3.0
Requires-Dist: datasets
Requires-Dist: optuna>=4.0.0
Requires-Dist: hydra-core>=1.3.0
Provides-Extra: dev
Requires-Dist: build; extra == "dev"
